le_baronysard_de_toolkit/__init__.py
le_baronysard_de_toolkit/main.py
le_baronysard_de_toolkit/vm.py
le_baronysard_de_toolkit-0.1.2.dist-info/METADATA
le_baronysard_de_toolkit-0.1.2.dist-info/WHEEL
le_baronysard_de_toolkit-0.1.2.dist-info/entry_points.txt
le_baronysard_de_toolkit-0.1.2.dist-info/RECORD
